hat/drivers/cosp/__init__.py
hat/drivers/icmp/endpoint.py
hat/drivers/serial/_native_serial.abi3.so
hat/drivers/cosp/common.py
hat/drivers/iec60870/encodings/iec101/__init__.py
hat/drivers/upnp/__init__.py
hat/drivers/cosp/encoder.py
hat/drivers/tcp.py
hat/drivers/iec104/common.py
hat/drivers/smpp/common.py
hat/drivers/cosp/connection.py
hat/drivers/iec61850/client/logger.py
hat/drivers/iec60870/apci/connection.py
hat/drivers/snmp/encoder/openssl.py
hat/drivers/modbus/master.py
hat/drivers/smpp/__init__.py
hat/drivers/smpp/client.py
hat/drivers/ssl/__init__.py
hat/drivers/snmp/encoder/asn1_repo.json
hat/drivers/icmp/__init__.py
hat/drivers/iec101/connection.py
hat/drivers/iec61850/manager/main.py
hat/drivers/snmp/manager/v2c.py
hat/drivers/cdt/runtime.py
hat/drivers/iec104/logger.py
hat/drivers/cdt/connection.py
hat/drivers/iec60870/link/encoder.py
hat/drivers/iec104/__init__.py
hat/drivers/snmp/trap/__init__.py
hat/drivers/iec61850/__init__.py
hat/drivers/snmp/manager/cli.py
hat/drivers/pnetgateway/transport.py
hat/drivers/snmp/trap/listener.py
hat/drivers/snmp/encoder/v3.py
hat/drivers/modbus/transport/encoder.py
hat/drivers/iec60870/link/common.py
hat/drivers/tpkt.py
hat/drivers/iec101/encoder.py
hat/drivers/mqtt/common.py
hat/drivers/ssl/_ssl.abi3.so
hat/drivers/iec60870/apci/logger.py
hat/drivers/snmp/trap/sender/__init__.py
hat/drivers/iec61850/manager/__main__.py
hat/drivers/snmp/agent.py
hat/drivers/iec60870/encodings/iec104/__init__.py
hat/drivers/snmp/trap/sender/v2c.py
hat/drivers/iec60870/link/unbalanced/master.py
hat/drivers/iec103/common.py
hat/drivers/iec60870/link/__init__.py
hat/drivers/iec60870/encodings/iec103/__init__.py
hat/drivers/__init__.py
hat/drivers/snmp/trap/sender/v1.py
hat/drivers/smpp/transport/encoder.py
hat/drivers/iec60870/encodings/iec101/common.py
hat/drivers/mqtt/client.py
hat/drivers/mqtt/transport/common.py
hat/drivers/smpp/transport/connection.py
hat/drivers/snmp/trap/sender/v3.py
hat_drivers-0.9.42.dist-info/LICENSE
hat_drivers-0.9.42.dist-info/entry_points.txt
hat_drivers-0.9.42.dist-info/METADATA
hat_drivers-0.9.42.dist-info/WHEEL
hat_drivers-0.9.42.dist-info/RECORD
