Metadata-Version: 2.1
Name: hat-drivers
Version: 0.9.42
Summary: Hat communication drivers
License: Apache-2.0
Classifier: Programming Language :: Python :: 3
Classifier: License :: OSI Approved :: Apache Software License
Provides-Extra: dev
Requires-Dist: aiohttp ~=3.10.11
Requires-Dist: hat-aio ~=0.7.12
Requires-Dist: hat-asn1 ~=0.7.0
Requires-Dist: hat-json ~=0.6.3
Requires-Dist: hat-sbs ~=0.7.5
Requires-Dist: hat-util ~=0.6.20
Requires-Dist: pyserial ~=3.5
Requires-Dist: hat-doit ~=0.16.2; extra == 'dev'
Requires-Dist: peru >=1.3.1; extra == 'dev'
Requires-Python: >=3.10
Project-URL: Homepage, http://hat-open.com
Project-URL: Repository, https://github.com/hat-open/hat-drivers.git
Project-URL: Documentation, http://hat-drivers.hat-open.com
